{
	"responseData": [
        {
            "CustomerId": 1,
            "CustomerCode": "C001",
            "FirstName": "Sundar",
            "LastName": "Ram",
            "Username": "Sundar Ram",
            "CompanyName": "AB Technology",
            "CustomerIndustry": "1",
            "Notes": "He gave his machine",
            "TaxType": "Rolling Stack",
            "IsLaborOnInvoice": "Yes",
            "Status": "Active",
            "StreetAddress": "Anna Street",
            "Email": "Sundar@gmail.com",
			"City": "chennai",
			"Zip":"123456",
            "GroupName": "Retailer",
            "CustomerType": "Personal",
            "Terms": "Net 15",
            "StateName": "Tamilnadu",
            "CountryName": "India",
            "PhoneNoPrimary": "100",
            "PhoneNoSecondary": "232",
            "IsContactAddress": 1,
            "IsShippingAddress": 1,
            "IsBillingAddress": 1,
            "AddressType": "Contact"
        },
        {
            "CustomerId": 2,
            "CustomerCode": "C002",
            "FirstName": "John",
            "LastName": "Peter",
            "Username": "John Peter",
            "CompanyName": "DC Technology",
            "CustomerIndustry": "1",
            "Notes": "He gave his Asset",
            "TaxType": "Rolling Stack",
            "IsLaborOnInvoice": "Yes",
            "Status": "Active",
            "StreetAddress": "james Street",
            "Email": "james@gmail.com",
            "City": "chennai",
			"Zip":"123456",
            "GroupName": "Retailer",
            "CustomerType": "Personal",
            "Terms": "Net 15",
            "StateName": "Tamilnadu",
            "CountryName": "India",
            "PhoneNoPrimary": "100",
            "PhoneNoSecondary": "232",
            "IsContactAddress": 1,
            "IsShippingAddress": 1,
            "IsBillingAddress": 1,
            "AddressType": "Contact"
        },
      {
            "CustomerId": 3,
            "CustomerCode": "C003",
            "FirstName": "Hari",
            "LastName": "Vengat",
            "Username": "Hari Vengat",
            "CompanyName": "Tech Technology",
            "CustomerIndustry": "1",
            "Notes": "He gave his Asset",
            "TaxType": "Rolling Stack",
            "IsLaborOnInvoice": "Yes",
            "Status": "Active",
            "StreetAddress": "Gandhi Street",
            "Email": "Gan@gmail.com",
            "City": "chennai",
			"Zip":"123456",
            "GroupName": "Retailer",
            "CustomerType": "Personal",
            "Terms": "Net 15",
            "StateName": "Tamilnadu",
            "CountryName": "India",
            "PhoneNoPrimary": "100",
            "PhoneNoSecondary": "232",
            "IsContactAddress": 1,
            "IsShippingAddress": 1,
            "IsBillingAddress": 1,
            "AddressType": "Contact"
        },
        {
            "CustomerId": 4,
            "CustomerCode": "C004",
            "FirstName": "vijay",
            "LastName": "Kumar",
            "Username": "Vijay Kumar",
            "CompanyName": "Test Technology",
            "CustomerIndustry": "1",
            "Notes": "He gave his Asset",
            "TaxType": "Rolling Stack",
            "IsLaborOnInvoice": "Yes",
            "Status": "Active",
            "StreetAddress": "Immanuvel Street",
            "Email": "vijay@gmail.com",
            "City": "chennai",
			"Zip":"123456",
            "GroupName": "Retailer",
            "CustomerType": "Personal",
            "Terms": "Net 15",
            "StateName": "Tamilnadu",
            "CountryName": "India",
            "PhoneNoPrimary": "100",
            "PhoneNoSecondary": "232",
            "IsContactAddress": 1,
            "IsShippingAddress": 1,
            "IsBillingAddress": 1,
            "AddressType": "Contact"
        },
        {
            "CustomerId": 5,
            "CustomerCode": "C005",
            "FirstName": "Dev",
            "LastName": "Kumar",
            "Username": "Dev Kumar",
            "CompanyName": "Dev Technology",
            "CustomerIndustry": "1",
            "Notes": "He gave his Asset",
            "TaxType": "Rolling Stack",
            "IsLaborOnInvoice": "Yes",
            "Status": "Active",
            "StreetAddress": "Bala Street",
            "Email": "Kumar@gmail.com",
            "City": "chennai",
			"Zip":"123456",
            "GroupName": "Retailer",
            "CustomerType": "Personal",
            "Terms": "Net 15",
            "StateName": "Tamilnadu",
            "CountryName": "India",
            "PhoneNoPrimary": "100",
            "PhoneNoSecondary": "232",
            "IsContactAddress": 1,
            "IsShippingAddress": 1,
            "IsBillingAddress": 1,
            "AddressType": "Contact"
        }
    ]
}